[
    {
        "resource": "allanime",
        "label": "Anime for Weebs"
    },
    {
        "resource": "painterboy",
        "label": "Painter Boy wazzup my man"
    },
    {
        "resource": "space",
        "label": "Space adventures"
    },
    {
        "resource": "doctorstrange",
        "label": "A spell for an eye"
    },
    {
        "resource": "colors",
        "label": "Colorful looking thing"
    },
    {
        "resource": "green",
        "label": "Hmmm those trees have green in 'em"
    },
    {
        "resource": "orange",
        "label": "Half dead clock looking thing"
    },
    {
        "resource": "luffy",
        "label": "I'm gonna be the king of the pirates"
    },
    {
        "resource": "deadpoop",
        "label": "I can grow my balls back unlike Wolverine"
    },
    {
        "label": "I can look at those all day",
        "url": "https://i.imgur.com/tLYSHmL.jpg"
    },
    {
        "label": "It is a 404",
        "url": "https://i.imgur.com/jdiejofei.jpg"
    }
]
